friday/__about__.py
friday/__init__.py
friday/_utils.py
friday/aggregator.py
friday/logger.py
friday/types.py
friday_logger-0.0.17.dist-info/METADATA
friday_logger-0.0.17.dist-info/WHEEL
friday_logger-0.0.17.dist-info/licenses/LICENSE.txt
friday_logger-0.0.17.dist-info/RECORD
