Metadata-Version: 2.3
Name: friday-logger
Version: 0.0.17
Project-URL: Documentation, https://github.com/kvqn/friday#readme
Project-URL: Issues, https://github.com/kvqn/friday/issues
Project-URL: Source, https://github.com/kvqn/friday
Author-email: Guneet Aggarwal <guneetaggarwal@gmail.com>
License-Expression: MIT
License-File: LICENSE.txt
Classifier: Development Status :: 4 - Beta
Classifier: Programming Language :: Python
Classifier: Programming Language :: Python :: 3.8
Classifier: Programming Language :: Python :: 3.9
Classifier: Programming Language :: Python :: 3.10
Classifier: Programming Language :: Python :: 3.11
Classifier: Programming Language :: Python :: 3.12
Classifier: Programming Language :: Python :: Implementation :: CPython
Classifier: Programming Language :: Python :: Implementation :: PyPy
Requires-Python: >=3.8
Requires-Dist: requests
